{
    "title": "fuerstengruft-15512",
    "gender": "m",
    "author": "André Schinkel",
    "author_birth": "1972",
    "poem": {
        "line.1": {
            "text": "Du steigst hinab, das Fahl der Särge"
        },
        "line.2": {
            "text": "Gibt sich geziert den Blicken hin;"
        },
        "line.3": {
            "text": "Die Mauern fliehn, mit kühler Stärke"
        },
        "line.4": {
            "text": "Geformt für einen Baldachin."
        },
        "line.5": {
            "text": "Du siehst dich um, die Fürsten ruhen,"
        },
        "line.6": {
            "text": "Und der Beschließer ruft dir nach:"
        },
        "line.7": {
            "text": "Hier schläft in Manns- und Kindertruhen"
        },
        "line.8": {
            "text": "Des Städtleins Glück und Ungemach!"
        },
        "line.9": {
            "text": "Du gehst hinein, der Brodem fängt dich;"
        },
        "line.10": {
            "text": "Das edle Holz des Meisters knackt,"
        },
        "line.11": {
            "text": "Du bist erregt, dein Atem senkt sich,"
        },
        "line.12": {
            "text": "Und legst die scheue Rose ab."
        }
    }
}