{
    "title": "rueckseite-eines-palastes-14391",
    "gender": "m",
    "author": "Carl-Christian Elze",
    "author_birth": "1974",
    "poem": {
        "line.1": {
            "text": "rückseite eines palastes"
        },
        "line.2": {
            "text": ": dunkel und eng, voller kot"
        },
        "line.3": {
            "text": "und elektrischer leitungen, unbegreiflicher apparaturen."
        },
        "line.4": {
            "text": "eidechsen kriechen die wände hinauf, rutschen aus auf salpeter"
        },
        "line.5": {
            "text": "und fangen sich wieder, im letzten moment, mit zitternden flanken."
        },
        "line.6": {
            "text": "ein heer von stacheln, das in die dunkelheiten ragt"
        },
        "line.7": {
            "text": "und jede landung bedroht: ein taubenjunges, das vom himmel fiel"
        },
        "line.8": {
            "text": "noch halbnackt taumelt es am grund und stiert in die ecken"
        },
        "line.9": {
            "text": "mit zuckendem kopf, sucht ein nest im universum der gasse."
        },
        "line.10": {
            "text": "auf einem vergitterten fenster, gleich über ihm balancierend"
        },
        "line.11": {
            "text": "die katze, die satt in ihre speisekammer blickt, satt für minuten."
        },
        "line.12": {
            "text": "calle corner: manchmal ein mensch, der durch die enge streift"
        },
        "line.13": {
            "text": "und seine hosen runterlässt und mit sich redet"
        },
        "line.14": {
            "text": "wie schon seit jahren nicht mehr. oder auch zwei:"
        },
        "line.15": {
            "text": "zwei menschen, mit regenschirmen, die sich wild verhaken."
        },
        "line.16": {
            "text": "am nächsten morgen: ein häufchen federn, knochenschimmer"
        },
        "line.17": {
            "text": "und wieder sonnenspeere, die im boden stecken, kinderschreie"
        },
        "line.18": {
            "text": "gepresst aus möwenköpfen .. als gäb es folterkammern"
        },
        "line.19": {
            "text": "die im himmel stehn, in einem becken"
        },
        "line.20": {
            "text": "von unverschämtem blau."
        }
    }
}