{
    "title": "alles-was-wir-tun-ist-musik-john-cage-13426",
    "author": "Volker Sielaff",
    "poem": {
        "line.1": {
            "text": "Der Regentag bietet sich an gebietet sich der Regentag  für eine Unternehmung das Tropfentrommeln der Tropfen ans Fenster ans gekippte Fenster Und die triefenden Blätter der trompetenartigen weißen Blumen weißen Blüten  in dem Garten unter dem gekippten Fenster: will nur zu Haus bleiben, sagst du und dem Regen lauschen älter als das Auge: der Gehörsinn blätternder umblätternder Regen draußen durchweichte Trompetenblumen Trompeten- blüten: dein Trommeln mit Fingern Fingerspitzen auf den Tisch auf das weiße Blatt Papier malst eine Blüte trompeten- artige einer weißen ungeschützten Unternehmung (Blüte:)  Spaziergang über die Dörfer hinaus im Regen."
        }
    }
}