{
    "title": "auslegung-5143",
    "gender": "m",
    "author": "Franzobel",
    "author_birth": "1967",
    "poem": {
        "line.1": {
            "text": "ssssssss"
        },
        "line.2": {
            "text": "swr ph"
        },
        "line.3": {
            "text": "swr wh"
        },
        "line.4": {
            "text": "swr mmm"
        },
        "line.5": {
            "text": "ssssssss"
        },
        "line.6": {
            "text": "swr schmmm"
        },
        "line.7": {
            "text": "ssssssss"
        },
        "line.8": {
            "text": "swr schmmmndgt"
        },
        "line.9": {
            "text": "ssssssss"
        },
        "line.10": {
            "text": "swr rklch ch gt"
        },
        "line.11": {
            "text": "chrrch"
        },
        "line.12": {
            "text": "chrr chrr"
        },
        "line.13": {
            "text": "hhh"
        },
        "line.14": {
            "text": "chrrr nd gt"
        }
    }
}