{
    "title": "beim-reimschmied-481",
    "gender": "m",
    "author": "Günter Saalmann",
    "author_birth": "1936",
    "poem": {
        "line.1": {
            "text": "Es poltert an des klugen Reim-"
        },
        "line.2": {
            "text": "schmieds Tor, er ist zum Glück daheim."
        },
        "line.3": {
            "text": "Da tritt herein ein müder Schim-"
        },
        "line.4": {
            "text": "mel: Meister, ach, mir geht es schlimm."
        },
        "line.5": {
            "text": "Ich bin das Flügelpferd, der Pe-"
        },
        "line.6": {
            "text": "gasus, doch lahm und flugunfäh-"
        },
        "line.7": {
            "text": "Zu dick! so unterbricht der Mei-"
        },
        "line.8": {
            "text": "ster ihn. Doch was ist schon dabei?"
        },
        "line.9": {
            "text": "Was braucht ein gutes Zugpferd Flü-"
        },
        "line.10": {
            "text": "gel! Ich beschlag dich, und dann: Hüh!"
        }
    }
}