{
    "title": "so-augenweide-achsen-und-fragt-sich-unten-15454",
    "gender": "w",
    "author": "Sandra Burkhardt",
    "author_birth": "1992",
    "poem": {
        "line.1": {
            "text": "Und fragt sich unten: Wer hat diese Hecke geschnippelt,"
        },
        "line.2": {
            "text": "und sie angehoben, sodass sie, wohin man schaut,"
        },
        "line.3": {
            "text": "den Blick verstellt? Man kommt nicht drum herum, nun"
        },
        "line.4": {
            "text": "über Ebenen zu grübeln: Als ließe sich, mit einem Griff,"
        },
        "line.5": {
            "text": "das Quadrat zum Kubus heben. Als ließe sich niemals anders"
        },
        "line.6": {
            "text": "als senkrecht zum Boden gehen und parallel zu ihm sehen."
        },
        "line.7": {
            "text": "Als rücke entlang der Hecken das Becken ab, als schiebe man"
        },
        "line.8": {
            "text": "alles vor sich her. Als befänden sich alle Ecken hier"
        },
        "line.9": {
            "text": "und Punkte in der Ferne in Wahrheit an derselben Stelle."
        },
        "line.10": {
            "text": "Und dann tritt man nach all den Treppen doch geradeaus."
        }
    }
}