{
    "title": "sadomasochistische-grammatik-der-traeume-732",
    "gender": "w",
    "author": "Silke Scheuermann",
    "author_birth": "1973",
    "poem": {
        "line.1": {
            "text": "Mit allem, was vom Indikativ in den Konjunktiv wechselt,"
        },
        "line.2": {
            "text": "legt die Nacht sich auf den Tagund kettet seine Hände oben"
        },
        "line.3": {
            "text": "ans Bett. Alles, was wir nicht gesagt haben, wächst in das"
        },
        "line.4": {
            "text": "Weiße der Haut ein, dort, wo die Schlingen das Blut sperren."
        },
        "line.5": {
            "text": "Ex machina schaltet das Mondlicht sich zu. Sprachfremd"
        },
        "line.6": {
            "text": "konjugieren wir allerknappste Alphabete."
        }
    }
}