{
    "title": "so-augenweide-achsen-man-trippelt-zu-weit-nach-links-15455",
    "gender": "w",
    "author": "Sandra Burkhardt",
    "author_birth": "1992",
    "poem": {
        "line.1": {
            "text": "Man trippelt zu weit nach links bis die Büsche wie Bäume"
        },
        "line.2": {
            "text": "wachsen, als gewaltige Waldwand entlang einer Geraden,"
        },
        "line.3": {
            "text": "und je gerader der Stamm, desto verzweigter der Zweig."
        },
        "line.4": {
            "text": "Was gelingt der Wildnis, und was gelingt ihr nicht? Sprachs:"
        },
        "line.5": {
            "text": "Leg jetzt den Kopf in den Nacken, bis du die Wipfel"
        },
        "line.6": {
            "text": "und schon wieder das Kies siehst. Besieht man aber"
        },
        "line.7": {
            "text": "die Blätter genauer, beginnt hier der Verfall: Viele Hölzer,"
        },
        "line.8": {
            "text": "die aus ihnen wuchern und drücken, Wipfel und zwei Rehe,"
        },
        "line.9": {
            "text": "die zurückblicken. Zwei Jäger, die in den Wald blicken,"
        },
        "line.10": {
            "text": "und springt einer in die Pfütze, fällt man selbst aus dem Bild."
        }
    }
}