{
    "title": "wochen-ankern-auf-ruempfen-guter-antennen-14878",
    "gender": "w",
    "author": "Dagmara Kraus",
    "author_birth": "1981",
    "poem": {
        "line.1": {
            "text": "wochen ankern auf rümpfen guter antennen und mein mane ratzt noch"
        },
        "line.2": {
            "text": "ich hab mir die strümpfe an den teppich genäht, um nicht von hier wegzurennen"
        },
        "line.3": {
            "text": "und die ewigkeit ist die witwe des todes; sie zerrt ein kinntau von bart hinter"
        },
        "line.4": {
            "text": "sich her"
        },
        "line.5": {
            "text": "sie rodet damit und sie rodet (nicht er, nein, der wär verwirkt)"
        },
        "line.6": {
            "text": "und klotho klaubt klumpatsch, kaut klumpatsch vor"
        },
        "line.7": {
            "text": "zum beispiel haselschienen fürs eichhörnchen zufall"
        },
        "line.8": {
            "text": "es ratscht, mahlt, tratscht, die mienen auf dem kien"
        },
        "line.9": {
            "text": "wochen ankern auf stümpfen guter antennen"
        },
        "line.10": {
            "text": "wie die tanne kratzt noch"
        },
        "line.11": {
            "text": "ich hab mir den kumpf schier am eppich versengt und da nicht mehr"
        },
        "line.12": {
            "text": "wegzukönnen"
        },
        "line.13": {
            "text": "ist doch gar nicht so flimm"
        }
    }
}