{
    "title": "ueber-die-erden-653",
    "categories": [
        "Lyrik f\u00fcr Kinder",
        "Natur",
        "Pflanzen"
    ],
    "gender": "m",
    "author": "Martin Auer",
    "poem": {
        "line.1": {
            "text": "\u00dcber die Erden mua\u00dft barfu\u00df gehn."
        },
        "line.2": {
            "text": "Ziagd'Schuach aus, die machen di blind!"
        },
        "line.3": {
            "text": "Dann kannst den Weg mit die Zechn sehn,"
        },
        "line.4": {
            "text": "des Wasser, den Wind..."
        },
        "line.5": {
            "text": "Sollst mit die Sohln auf d'Staner steign,"
        },
        "line.6": {
            "text": "mit der nackerten Haut."
        },
        "line.7": {
            "text": "Wird dir die Erden aa bald zeign,"
        },
        "line.8": {
            "text": "da\u00dfs'dirvertraut."
        },
        "line.9": {
            "text": "Gsp\u00fcr des nasse Gras auf die F\u00fca\u00df,"
        },
        "line.10": {
            "text": "gsp\u00fcr, wie trocken is der Staub."
        },
        "line.11": {
            "text": "Gsp\u00fcr, wie dich streichelt das Moos so s\u00fca\u00df,"
        },
        "line.12": {
            "text": "gsp\u00fcr, wie's knistert im Laub."
        },
        "line.13": {
            "text": "In 'n Bach mua\u00dft einesteign,"
        },
        "line.14": {
            "text": "durchs Wasser mua\u00dft auffegehn,"
        },
        "line.15": {
            "text": "untern Wasserfall mua\u00dft di stelln mit 'm Gsicht in die H\u00f6h,"
        },
        "line.16": {
            "text": "mit der Wangen auf d' Erd in die Sunn di legn."
        },
        "line.17": {
            "text": "Lieg ganz still, riach die Erden und gsp\u00fcr,"
        },
        "line.18": {
            "text": "wie aufsteigt aus ihr a riesige Ruah."
        },
        "line.19": {
            "text": "Und dann is die Erden ganz nah bei dir"
        },
        "line.20": {
            "text": "und du wa\u00dft, du gh\u00f6rst zu allem dazua."
        },
        "line.21": {
            "text": "\u00dcber die Erde"
        },
        "line.22": {
            "text": "\u00dcber die Erde sollst du barfu\u00df gehen."
        },
        "line.23": {
            "text": "Zieh die Schuhe aus, Schuhe machen dich blind."
        },
        "line.24": {
            "text": "Du kannst doch den Weg mit deinen Zehen sehen"
        },
        "line.25": {
            "text": "Auch das Wasser und den Wind."
        },
        "line.26": {
            "text": "Sollst mit deinen Sohlen die Sterne ber\u00fchren,"
        },
        "line.27": {
            "text": "mit ganz nackter Haut."
        },
        "line.28": {
            "text": "Dann wirst du bald sp\u00fcren,"
        },
        "line.29": {
            "text": "da\u00df dir die Erde vertraut."
        },
        "line.30": {
            "text": "Sp\u00fcr das nasse Gras unter deinen F\u00fc\u00dfen"
        },
        "line.31": {
            "text": "und den trockenen Staub."
        },
        "line.32": {
            "text": "La\u00df dir vom Moos die Sohlen streicheln und k\u00fcssen"
        },
        "line.33": {
            "text": "und f\u00fchl das Knistern im Laub."
        },
        "line.34": {
            "text": "Steig hinein, steig hinein in den Bach"
        },
        "line.35": {
            "text": "und lauf aufw\u00e4rts dem Wasser entgegen."
        },
        "line.36": {
            "text": "Halt dein Gesicht unter den Wasserfall."
        },
        "line.37": {
            "text": "Und dann sollst du dich in die Sonne legen."
        },
        "line.38": {
            "text": "Leg deine Wange an die Erde, riech ihren Duft und sp\u00fcr,"
        },
        "line.39": {
            "text": "wie aufsteigt aus ihr eine ganz gro\u00dfe Ruh."
        },
        "line.40": {
            "text": "Und dann ist die Erde ganz nah bei dir,"
        },
        "line.41": {
            "text": "und du wei\u00dft: Du bist ein Teil von Allem und geh\u00f6rst dazu."
        }
    }
}